homeseer_client/__init__.py
homeseer_client/homeseer.py
homeseer_client-0.1.2.dist-info/METADATA
homeseer_client-0.1.2.dist-info/WHEEL
homeseer_client-0.1.2.dist-info/top_level.txt
homeseer_client-0.1.2.dist-info/RECORD
