Metadata-Version: 2.4
Name: homeseer-client
Version: 0.1.2
Summary: A thin wrapper around the Homeseer HTTP JSON API
Author: John Ritsema
License-Expression: MIT
Project-URL: Homepage, https://github.com/jritsema/homeseer-python-client
Project-URL: Bug Tracker, https://github.com/jritsema/homeseer-python-client/issues
Project-URL: Documentation, https://github.com/jritsema/homeseer-python-client#readme
Project-URL: Source Code, https://github.com/jritsema/homeseer-python-client
Classifier: Development Status :: 3 - Alpha
Classifier: Intended Audience :: Developers
Classifier: Operating System :: OS Independent
Classifier: Programming Language :: Python :: 3
Classifier: Programming Language :: Python :: 3.8
Classifier: Programming Language :: Python :: 3.9
Classifier: Programming Language :: Python :: 3.10
Classifier: Programming Language :: Python :: 3.11
Classifier: Programming Language :: Python :: 3.12
Classifier: Programming Language :: Python :: 3.13
Requires-Python: >=3.8
Requires-Dist: httpx
Provides-Extra: dev
Requires-Dist: pytest; extra == "dev"
Requires-Dist: pytest-cov; extra == "dev"
Requires-Dist: black; extra == "dev"
Requires-Dist: flake8; extra == "dev"
Requires-Dist: mypy; extra == "dev"
